{
  "id": "text_asset",
  "type": "SharedSlice",
  "name": "TextAsset",
  "description": "TextAsset",
  "variations": [
    {
      "id": "default",
      "name": "Default theme",
      "docURL": "...",
      "version": "sktwi1xtmkfgx8626",
      "description": "TextAsset",
      "primary": {
        "theme": {
          "type": "Select",
          "config": {
            "label": "Theme",
            "placeholder": "Select a theme....",
            "options": ["dark", "light", "blue"],
            "default_value": "dark"
          }
        },
        "title": {
          "type": "StructuredText",
          "config": {
            "label": "Title",
            "placeholder": "Enter title...",
            "allowTargetBlank": false,
            "single": "heading3"
          }
        },
        "label": {
          "type": "StructuredText",
          "config": {
            "label": "Label",
            "placeholder": "Enter label...",
            "allowTargetBlank": false,
            "single": "heading2"
          }
        },
        "text": {
          "type": "StructuredText",
          "config": {
            "label": "Text",
            "placeholder": "Enter text...",
            "allowTargetBlank": true,
            "multi": "paragraph,strong,em,hyperlink"
          }
        },
        "image": {
          "type": "Image",
          "config": {
            "label": "Image",
            "constraint": {},
            "thumbnails": []
          }
        }
      },
      "items": {},
      "imageUrl": "https://images.prismic.io/slice-machine/621a5ec4-0387-4bc5-9860-2dd46cbc07cd_default_ss.png?auto=compress,format"
    }
  ]
}
